{
  "project_info": {
    "project_number": "122688802398",
    "project_id": "studyfellow-42d35",
    "storage_bucket": "studyfellow-42d35.firebasestorage.app"
  },
  "client": [
    {
      "client_info": {
        "mobilesdk_app_id": "1:122688802398:android:74fb59f05ef8e867ffaecf",
        "android_client_info": {
          "package_name": "com.example.studyfellow_flutter"
        }
      },
      "oauth_client": [],
      "api_key": [
        {
          "current_key": "AIzaSyDT_thGnvUFkWmTuexWGEvEq170-K-FdDs"
        }
      ],
      "services": {
        "appinvite_service": {
          "other_platform_oauth_client": []
        }
      }
    }
  ],
  "configuration_version": "1"
}